clr_loader/__init__.py
clr_loader/hostfxr.py
clr_loader/mono.py
clr_loader/netfx.py
clr_loader/types.py
clr_loader/ffi/__init__.py
clr_loader/ffi/hostfxr.py
clr_loader/ffi/mono.py
clr_loader/ffi/netfx.py
clr_loader/ffi/dlls/amd64/ClrLoader.dll
clr_loader/ffi/dlls/amd64/ClrLoader.pdb
clr_loader/ffi/dlls/x86/ClrLoader.dll
clr_loader/ffi/dlls/x86/ClrLoader.pdb
clr_loader/util/__init__.py
clr_loader/util/clr_error.py
clr_loader/util/coreclr_errors.py
clr_loader/util/find.py
clr_loader/util/hostfxr_errors.py
clr_loader/util/runtime_spec.py
clr_loader-0.2.7.post0.dist-info/METADATA
clr_loader-0.2.7.post0.dist-info/WHEEL
clr_loader-0.2.7.post0.dist-info/top_level.txt
clr_loader-0.2.7.post0.dist-info/RECORD
